slidemovie/__init__.py
slidemovie/cli.py
slidemovie/core.py
slidemovie-0.3.0.dist-info/licenses/LICENSE
slidemovie-0.3.0.dist-info/METADATA
slidemovie-0.3.0.dist-info/WHEEL
slidemovie-0.3.0.dist-info/entry_points.txt
slidemovie-0.3.0.dist-info/top_level.txt
slidemovie-0.3.0.dist-info/RECORD
