Metadata-Version: 2.4
Name: slidemovie
Version: 0.3.0
Summary: Markdown and PowerPoint to narration video generator
Author: Katsutoshi Seki
License-Expression: MIT
Project-URL: Homepage, https://sekika.github.io/slidemovie/
Project-URL: Source, https://github.com/sekika/slidemovie
Keywords: powerpoint,markdown,video,tts,presentation,automation
Classifier: Development Status :: 4 - Beta
Classifier: Intended Audience :: Developers
Classifier: Intended Audience :: Education
Classifier: Operating System :: OS Independent
Classifier: Programming Language :: Python :: 3
Classifier: Programming Language :: Python :: 3.8
Classifier: Programming Language :: Python :: 3.9
Classifier: Programming Language :: Python :: 3.10
Classifier: Programming Language :: Python :: 3.11
Classifier: Programming Language :: Python :: 3.12
Classifier: Programming Language :: Python :: 3.13
Classifier: Topic :: Multimedia :: Video
Classifier: Topic :: Multimedia :: Sound/Audio :: Speech
Classifier: Topic :: Office/Business :: Office Suites
Requires-Python: >=3.8
License-File: LICENSE
Requires-Dist: multiai-tts
Requires-Dist: pptxtoimages
Dynamic: license-file
